[
  {
    "code": "male_1",
    "spriteIndex": 0,
    "gender": "male",
    "ageCategory": "adult",
    "outfit": {
      "topColor": "grey",
      "bottomColor": "black",
      "type": null,
      "hat": null
    },
    "hair": null
  },
  {
    "code": "male_2",
    "spriteIndex": 1,
    "gender": "male",
    "ageCategory": "adult",
    "outfit": {
      "topColor": "green",
      "bottomColor": "green",
      "type": null,
      "hat": null
    },
    "hair": {
      "type": "short",
      "color": "brown"
    }
  },
  {
    "code": "woman_1",
    "spriteIndex": 2,
    "gender": "woman",
    "ageCategory": "adult",
    "outfit": {
      "topColor": "red",
      "bottomColor": "blue",
      "type": null,
      "hat": null
    },
    "hair": {
      "type": "long",
      "color": "brown"
    }
  },
  {
    "code": "male_3",
    "spriteIndex": 3,
    "gender": "male",
    "ageCategory": "old",
    "outfit": {
      "topColor": "brown",
      "bottomColor": "green",
      "type": null,
      "hat": null
    },
    "hair": {
      "type": "short",
      "color": "grey"
    }
  },
  {
    "code": "male_4",
    "spriteIndex": 4,
    "gender": "male",
    "ageCategory": "adult",
    "outfit": {
      "topColor": "grey",
      "bottomColor": "blue",
      "type": "builder",
      "hat": {
        "color": "yellow",
        "type": "helmet"
      }
    },
    "hair": {
      "type": "short",
      "color": "black"
    }
  },
  {
    "code": "woman_2",
    "spriteIndex": 5,
    "gender": "woman",
    "ageCategory": "adult",
    "outfit": {
      "topColor": "brown",
      "bottomColor": "grey",
      "type": null,
      "hat": {
        "color": "orange",
        "type": "headband"
      }
    },
    "hair": {
      "type": "long",
      "color": "black"
    }
  }
]